[
  {
    "id": 1,
    "title": "Mega Bloks Mega Blocks Building Blocks",
    "description": "Buy the Mega Bloks Mega Blocks Building Blocks from Mega Bloks. Building Blocks engineered for quality and value. Ideal for toys needs.",
    "price": 105.79,
    "category": "Toys",
    "rating": 2.4,
    "stock": 36,
    "brand": "Mega Bloks",
    "createdAt": "2025-06-09T21:59:09.743Z"
  },
  {
    "id": 2,
    "title": "Hasbro Galaxy Fighter Action Figure",
    "description": "Buy the Hasbro Galaxy Fighter Action Figure from Hasbro. Action Figure engineered for quality and value. Ideal for toys needs.",
    "price": 70.91,
    "category": "Toys",
    "rating": 4.9,
    "stock": 313,
    "brand": "Hasbro",
    "createdAt": "2025-12-15T19:54:22.262Z"
  },
  {
    "id": 3,
    "title": "New Balance Fresh Foam Running Shoes",
    "description": "Buy the New Balance Fresh Foam Running Shoes from New Balance. Running Shoes engineered for quality and value. Ideal for sports needs.",
    "price": 171.22,
    "category": "Sports",
    "rating": 4.1,
    "stock": 393,
    "brand": "New Balance",
    "createdAt": "2025-07-21T08:04:37.633Z"
  },
  {
    "id": 4,
    "title": "Nike ZoomX Running Shoes",
    "description": "Buy the Nike ZoomX Running Shoes from Nike. Running Shoes engineered for quality and value. Ideal for sports needs.",
    "price": 194.49,
    "category": "Sports",
    "rating": 1.4,
    "stock": 139,
    "brand": "Nike",
    "createdAt": "2026-02-20T18:26:02.741Z"
  },
  {
    "id": 5,
    "title": "Hoover Cyclone 3000 Vacuum Cleaner",
    "description": "Buy the Hoover Cyclone 3000 Vacuum Cleaner from Hoover. Vacuum Cleaner engineered for quality and value. Ideal for home needs.",
    "price": 49.97,
    "category": "Home",
    "rating": 3.7,
    "stock": 404,
    "brand": "Hoover",
    "createdAt": "2026-02-26T23:56:15.040Z"
  },
  {
    "id": 6,
    "title": "Shark Cyclone 3000 Vacuum Cleaner",
    "description": "Buy the Shark Cyclone 3000 Vacuum Cleaner from Shark. Vacuum Cleaner engineered for quality and value. Ideal for home needs.",
    "price": 359.53,
    "category": "Home",
    "rating": 4.6,
    "stock": 293,
    "brand": "Shark",
    "createdAt": "2025-05-13T08:34:24.680Z"
  },
  {
    "id": 7,
    "title": "Nike Gel-Nimbus Running Shoes",
    "description": "Buy the Nike Gel-Nimbus Running Shoes from Nike. Running Shoes engineered for quality and value. Ideal for sports needs.",
    "price": 187.15,
    "category": "Sports",
    "rating": 2.2,
    "stock": 47,
    "brand": "Nike",
    "createdAt": "2025-05-08T06:44:55.292Z"
  },
  {
    "id": 8,
    "title": "Lululemon ProGrip Yoga Mat",
    "description": "Buy the Lululemon ProGrip Yoga Mat from Lululemon. Yoga Mat engineered for quality and value. Ideal for sports needs.",
    "price": 31.24,
    "category": "Sports",
    "rating": 4,
    "stock": 213,
    "brand": "Lululemon",
    "createdAt": "2025-06-22T18:44:41.651Z"
  },
  {
    "id": 9,
    "title": "ASICS Fresh Foam Running Shoes",
    "description": "Buy the ASICS Fresh Foam Running Shoes from ASICS. Running Shoes engineered for quality and value. Ideal for sports needs.",
    "price": 243.39,
    "category": "Sports",
    "rating": 4.1,
    "stock": 149,
    "brand": "ASICS",
    "createdAt": "2026-03-16T08:28:20.034Z"
  },
  {
    "id": 10,
    "title": "KitchenAid ProBlend Blender",
    "description": "Buy the KitchenAid ProBlend Blender from KitchenAid. Blender engineered for quality and value. Ideal for home needs.",
    "price": 333.43,
    "category": "Home",
    "rating": 4.7,
    "stock": 116,
    "brand": "KitchenAid",
    "createdAt": "2025-06-09T15:32:35.019Z"
  },
  {
    "id": 11,
    "title": "W.W. Norton Sapiens Non-Fiction",
    "description": "Buy the W.W. Norton Sapiens Non-Fiction from W.W. Norton. Non-Fiction engineered for quality and value. Ideal for books needs.",
    "price": 39.87,
    "category": "Books",
    "rating": 4.8,
    "stock": 271,
    "brand": "W.W. Norton",
    "createdAt": "2026-03-12T02:39:15.299Z"
  },
  {
    "id": 12,
    "title": "Hoover PowerSweep Vacuum Cleaner",
    "description": "Buy the Hoover PowerSweep Vacuum Cleaner from Hoover. Vacuum Cleaner engineered for quality and value. Ideal for home needs.",
    "price": 569.41,
    "category": "Home",
    "rating": 4.2,
    "stock": 486,
    "brand": "Hoover",
    "createdAt": "2025-04-29T05:12:05.009Z"
  },
  {
    "id": 13,
    "title": "Nike ZoomX Running Shoes",
    "description": "Buy the Nike ZoomX Running Shoes from Nike. Running Shoes engineered for quality and value. Ideal for sports needs.",
    "price": 247.47,
    "category": "Sports",
    "rating": 2.8,
    "stock": 81,
    "brand": "Nike",
    "createdAt": "2026-03-06T11:04:10.664Z"
  },
  {
    "id": 14,
    "title": "HarperCollins The Last Kingdom Fiction Book",
    "description": "Buy the HarperCollins The Last Kingdom Fiction Book from HarperCollins. Fiction Book engineered for quality and value. Ideal for books needs.",
    "price": 29.21,
    "category": "Books",
    "rating": 2.3,
    "stock": 484,
    "brand": "HarperCollins",
    "createdAt": "2025-05-22T14:53:20.281Z"
  },
  {
    "id": 15,
    "title": "Dyson Cyclone 3000 Vacuum Cleaner",
    "description": "Buy the Dyson Cyclone 3000 Vacuum Cleaner from Dyson. Vacuum Cleaner engineered for quality and value. Ideal for home needs.",
    "price": 593.3,
    "category": "Home",
    "rating": 1.1,
    "stock": 329,
    "brand": "Dyson",
    "createdAt": "2025-03-30T12:07:19.084Z"
  },
  {
    "id": 16,
    "title": "Neutrogena Daily Cream Moisturizer",
    "description": "Buy the Neutrogena Daily Cream Moisturizer from Neutrogena. Moisturizer engineered for quality and value. Ideal for beauty needs.",
    "price": 32.34,
    "category": "Beauty",
    "rating": 1,
    "stock": 320,
    "brand": "Neutrogena",
    "createdAt": "2025-08-14T21:09:44.644Z"
  },
  {
    "id": 17,
    "title": "Lenovo MacBook Air Laptop",
    "description": "Buy the Lenovo MacBook Air Laptop from Lenovo. Laptop engineered for quality and value. Ideal for electronics needs.",
    "price": 1711.94,
    "category": "Electronics",
    "rating": 4.9,
    "stock": 412,
    "brand": "Lenovo",
    "createdAt": "2025-05-19T17:12:13.206Z"
  },
  {
    "id": 18,
    "title": "Cetaphil Daily Cream Moisturizer",
    "description": "Buy the Cetaphil Daily Cream Moisturizer from Cetaphil. Moisturizer engineered for quality and value. Ideal for beauty needs.",
    "price": 36.36,
    "category": "Beauty",
    "rating": 3.6,
    "stock": 439,
    "brand": "Cetaphil",
    "createdAt": "2025-05-09T20:14:14.679Z"
  },
  {
    "id": 19,
    "title": "Samsung OLED CX 4K TV",
    "description": "Buy the Samsung OLED CX 4K TV from Samsung. 4K TV engineered for quality and value. Ideal for electronics needs.",
    "price": 1264.26,
    "category": "Electronics",
    "rating": 2.9,
    "stock": 0,
    "brand": "Samsung",
    "createdAt": "2026-01-09T23:41:12.509Z"
  },
  {
    "id": 20,
    "title": "Bose WH-1000XM4 Wireless Headphones",
    "description": "Buy the Bose WH-1000XM4 Wireless Headphones from Bose. Wireless Headphones engineered for quality and value. Ideal for electronics needs.",
    "price": 264.59,
    "category": "Electronics",
    "rating": 4.7,
    "stock": 259,
    "brand": "Bose",
    "createdAt": "2025-09-09T06:43:32.576Z"
  },
  {
    "id": 21,
    "title": "Dyson PowerSweep Vacuum Cleaner",
    "description": "Buy the Dyson PowerSweep Vacuum Cleaner from Dyson. Vacuum Cleaner engineered for quality and value. Ideal for home needs.",
    "price": 584.01,
    "category": "Home",
    "rating": 1.7,
    "stock": 225,
    "brand": "Dyson",
    "createdAt": "2025-07-14T10:31:05.456Z"
  },
  {
    "id": 22,
    "title": "Random House The Silent Patient Fiction Book",
    "description": "Buy the Random House The Silent Patient Fiction Book from Random House. Fiction Book engineered for quality and value. Ideal for books needs.",
    "price": 27.41,
    "category": "Books",
    "rating": 4.5,
    "stock": 401,
    "brand": "Random House",
    "createdAt": "2025-08-10T03:32:36.885Z"
  },
  {
    "id": 23,
    "title": "Samsung Galaxy Watch 4 Smartwatch",
    "description": "Buy the Samsung Galaxy Watch 4 Smartwatch from Samsung. Smartwatch engineered for quality and value. Ideal for electronics needs.",
    "price": 492.01,
    "category": "Electronics",
    "rating": 1.2,
    "stock": 327,
    "brand": "Samsung",
    "createdAt": "2025-12-05T11:44:17.687Z"
  },
  {
    "id": 24,
    "title": "Mattel Hero Series Action Figure",
    "description": "Buy the Mattel Hero Series Action Figure from Mattel. Action Figure engineered for quality and value. Ideal for toys needs.",
    "price": 63.69,
    "category": "Toys",
    "rating": 3.5,
    "stock": 188,
    "brand": "Mattel",
    "createdAt": "2026-01-22T02:11:20.850Z"
  },
  {
    "id": 25,
    "title": "Samsung Galaxy Watch 4 Smartwatch",
    "description": "Buy the Samsung Galaxy Watch 4 Smartwatch from Samsung. Smartwatch engineered for quality and value. Ideal for electronics needs.",
    "price": 403.37,
    "category": "Electronics",
    "rating": 3.2,
    "stock": 7,
    "brand": "Samsung",
    "createdAt": "2025-07-17T04:37:23.556Z"
  },
  {
    "id": 26,
    "title": "W.W. Norton Atomic Habits Non-Fiction",
    "description": "Buy the W.W. Norton Atomic Habits Non-Fiction from W.W. Norton. Non-Fiction engineered for quality and value. Ideal for books needs.",
    "price": 34.76,
    "category": "Books",
    "rating": 1.1,
    "stock": 137,
    "brand": "W.W. Norton",
    "createdAt": "2026-01-28T09:24:31.998Z"
  },
  {
    "id": 27,
    "title": "Google Galaxy S21 Smartphone",
    "description": "Buy the Google Galaxy S21 Smartphone from Google. Smartphone engineered for quality and value. Ideal for electronics needs.",
    "price": 916.68,
    "category": "Electronics",
    "rating": 4.7,
    "stock": 2,
    "brand": "Google",
    "createdAt": "2025-05-03T17:24:21.793Z"
  },
  {
    "id": 28,
    "title": "Mega Bloks Classic Bricks Building Blocks",
    "description": "Buy the Mega Bloks Classic Bricks Building Blocks from Mega Bloks. Building Blocks engineered for quality and value. Ideal for toys needs.",
    "price": 188.39,
    "category": "Toys",
    "rating": 1.9,
    "stock": 182,
    "brand": "Mega Bloks",
    "createdAt": "2026-01-28T07:16:26.407Z"
  },
  {
    "id": 29,
    "title": "New Balance ZoomX Running Shoes",
    "description": "Buy the New Balance ZoomX Running Shoes from New Balance. Running Shoes engineered for quality and value. Ideal for sports needs.",
    "price": 52.62,
    "category": "Sports",
    "rating": 2.9,
    "stock": 394,
    "brand": "New Balance",
    "createdAt": "2025-06-07T09:06:24.109Z"
  },
  {
    "id": 30,
    "title": "KitchenAid ProBlend Blender",
    "description": "Buy the KitchenAid ProBlend Blender from KitchenAid. Blender engineered for quality and value. Ideal for home needs.",
    "price": 315.89,
    "category": "Home",
    "rating": 3.7,
    "stock": 52,
    "brand": "KitchenAid",
    "createdAt": "2025-05-10T17:42:10.076Z"
  },
  {
    "id": 31,
    "title": "Manduka EcoMat Yoga Mat",
    "description": "Buy the Manduka EcoMat Yoga Mat from Manduka. Yoga Mat engineered for quality and value. Ideal for sports needs.",
    "price": 65.81,
    "category": "Sports",
    "rating": 4.4,
    "stock": 428,
    "brand": "Manduka",
    "createdAt": "2025-07-11T13:55:24.831Z"
  },
  {
    "id": 32,
    "title": "Neutrogena HydraBoost Moisturizer",
    "description": "Buy the Neutrogena HydraBoost Moisturizer from Neutrogena. Moisturizer engineered for quality and value. Ideal for beauty needs.",
    "price": 41.94,
    "category": "Beauty",
    "rating": 1.4,
    "stock": 106,
    "brand": "Neutrogena",
    "createdAt": "2025-06-15T01:19:28.477Z"
  },
  {
    "id": 33,
    "title": "LG Bravia X90J 4K TV",
    "description": "Buy the LG Bravia X90J 4K TV from LG. 4K TV engineered for quality and value. Ideal for electronics needs.",
    "price": 631.73,
    "category": "Electronics",
    "rating": 4.8,
    "stock": 310,
    "brand": "LG",
    "createdAt": "2025-06-16T23:57:32.756Z"
  },
  {
    "id": 34,
    "title": "Lululemon EcoMat Yoga Mat",
    "description": "Buy the Lululemon EcoMat Yoga Mat from Lululemon. Yoga Mat engineered for quality and value. Ideal for sports needs.",
    "price": 20.25,
    "category": "Sports",
    "rating": 4.8,
    "stock": 444,
    "brand": "Lululemon",
    "createdAt": "2025-04-11T09:05:49.071Z"
  },
  {
    "id": 35,
    "title": "Random House The Silent Patient Fiction Book",
    "description": "Buy the Random House The Silent Patient Fiction Book from Random House. Fiction Book engineered for quality and value. Ideal for books needs.",
    "price": 9.26,
    "category": "Books",
    "rating": 4.6,
    "stock": 16,
    "brand": "Random House",
    "createdAt": "2025-07-19T16:23:31.372Z"
  },
  {
    "id": 36,
    "title": "Mega Bloks Mega Blocks Building Blocks",
    "description": "Buy the Mega Bloks Mega Blocks Building Blocks from Mega Bloks. Building Blocks engineered for quality and value. Ideal for toys needs.",
    "price": 54.8,
    "category": "Toys",
    "rating": 2.2,
    "stock": 464,
    "brand": "Mega Bloks",
    "createdAt": "2025-12-08T15:17:04.908Z"
  },
  {
    "id": 37,
    "title": "Cetaphil HydraBoost Moisturizer",
    "description": "Buy the Cetaphil HydraBoost Moisturizer from Cetaphil. Moisturizer engineered for quality and value. Ideal for beauty needs.",
    "price": 33.6,
    "category": "Beauty",
    "rating": 5,
    "stock": 499,
    "brand": "Cetaphil",
    "createdAt": "2025-11-07T02:59:18.712Z"
  },
  {
    "id": 38,
    "title": "Decathlon EcoMat Yoga Mat",
    "description": "Buy the Decathlon EcoMat Yoga Mat from Decathlon. Yoga Mat engineered for quality and value. Ideal for sports needs.",
    "price": 13.69,
    "category": "Sports",
    "rating": 4.5,
    "stock": 35,
    "brand": "Decathlon",
    "createdAt": "2025-06-16T20:24:16.782Z"
  },
  {
    "id": 39,
    "title": "Hasbro Hero Series Action Figure",
    "description": "Buy the Hasbro Hero Series Action Figure from Hasbro. Action Figure engineered for quality and value. Ideal for toys needs.",
    "price": 55.97,
    "category": "Toys",
    "rating": 4.1,
    "stock": 350,
    "brand": "Hasbro",
    "createdAt": "2025-08-27T09:15:07.987Z"
  },
  {
    "id": 40,
    "title": "Hasbro Classic Bricks Building Blocks",
    "description": "Buy the Hasbro Classic Bricks Building Blocks from Hasbro. Building Blocks engineered for quality and value. Ideal for toys needs.",
    "price": 156.42,
    "category": "Toys",
    "rating": 2.8,
    "stock": 259,
    "brand": "Hasbro",
    "createdAt": "2025-12-30T08:59:48.113Z"
  },
  {
    "id": 41,
    "title": "Sony QC35 II Wireless Headphones",
    "description": "Buy the Sony QC35 II Wireless Headphones from Sony. Wireless Headphones engineered for quality and value. Ideal for electronics needs.",
    "price": 244.22,
    "category": "Electronics",
    "rating": 2.8,
    "stock": 26,
    "brand": "Sony",
    "createdAt": "2025-11-26T04:37:06.868Z"
  },
  {
    "id": 42,
    "title": "Samsung OLED CX 4K TV",
    "description": "Buy the Samsung OLED CX 4K TV from Samsung. 4K TV engineered for quality and value. Ideal for electronics needs.",
    "price": 869.32,
    "category": "Electronics",
    "rating": 2.2,
    "stock": 302,
    "brand": "Samsung",
    "createdAt": "2025-11-05T00:19:26.492Z"
  },
  {
    "id": 43,
    "title": "L'Oreal Satin Lipstick",
    "description": "Buy the L'Oreal Satin Lipstick from L'Oreal. Lipstick engineered for quality and value. Ideal for beauty needs.",
    "price": 26.22,
    "category": "Beauty",
    "rating": 2.4,
    "stock": 384,
    "brand": "L'Oreal",
    "createdAt": "2025-05-22T08:34:36.574Z"
  },
  {
    "id": 44,
    "title": "Mattel Hero Series Action Figure",
    "description": "Buy the Mattel Hero Series Action Figure from Mattel. Action Figure engineered for quality and value. Ideal for toys needs.",
    "price": 60.89,
    "category": "Toys",
    "rating": 1.4,
    "stock": 155,
    "brand": "Mattel",
    "createdAt": "2026-02-10T11:27:24.525Z"
  },
  {
    "id": 45,
    "title": "L'Oreal Satin Lipstick",
    "description": "Buy the L'Oreal Satin Lipstick from L'Oreal. Lipstick engineered for quality and value. Ideal for beauty needs.",
    "price": 24.59,
    "category": "Beauty",
    "rating": 1.9,
    "stock": 85,
    "brand": "L'Oreal",
    "createdAt": "2025-12-23T09:15:35.748Z"
  },
  {
    "id": 46,
    "title": "HarperCollins Midnight Library Fiction Book",
    "description": "Buy the HarperCollins Midnight Library Fiction Book from HarperCollins. Fiction Book engineered for quality and value. Ideal for books needs.",
    "price": 26.79,
    "category": "Books",
    "rating": 1.4,
    "stock": 292,
    "brand": "HarperCollins",
    "createdAt": "2025-07-15T07:11:45.808Z"
  },
  {
    "id": 47,
    "title": "Apple Pixel 5 Smartphone",
    "description": "Buy the Apple Pixel 5 Smartphone from Apple. Smartphone engineered for quality and value. Ideal for electronics needs.",
    "price": 437.49,
    "category": "Electronics",
    "rating": 1.3,
    "stock": 151,
    "brand": "Apple",
    "createdAt": "2025-07-31T07:32:19.209Z"
  },
  {
    "id": 48,
    "title": "Converse Ultraboost Sneakers",
    "description": "Buy the Converse Ultraboost Sneakers from Converse. Sneakers engineered for quality and value. Ideal for clothing needs.",
    "price": 203.31,
    "category": "Clothing",
    "rating": 2.4,
    "stock": 149,
    "brand": "Converse",
    "createdAt": "2025-05-23T09:20:23.261Z"
  },
  {
    "id": 49,
    "title": "New Balance Fresh Foam Running Shoes",
    "description": "Buy the New Balance Fresh Foam Running Shoes from New Balance. Running Shoes engineered for quality and value. Ideal for sports needs.",
    "price": 120.53,
    "category": "Sports",
    "rating": 1.9,
    "stock": 55,
    "brand": "New Balance",
    "createdAt": "2025-10-03T22:05:05.536Z"
  },
  {
    "id": 50,
    "title": "KitchenAid SmoothieX Blender",
    "description": "Buy the KitchenAid SmoothieX Blender from KitchenAid. Blender engineered for quality and value. Ideal for home needs.",
    "price": 112.82,
    "category": "Home",
    "rating": 3.8,
    "stock": 492,
    "brand": "KitchenAid",
    "createdAt": "2025-05-18T23:26:11.823Z"
  },
  {
    "id": 51,
    "title": "ASICS Fresh Foam Running Shoes",
    "description": "Buy the ASICS Fresh Foam Running Shoes from ASICS. Running Shoes engineered for quality and value. Ideal for sports needs.",
    "price": 97.57,
    "category": "Sports",
    "rating": 2.1,
    "stock": 170,
    "brand": "ASICS",
    "createdAt": "2025-09-21T17:05:44.037Z"
  },
  {
    "id": 52,
    "title": "Olay HydraBoost Moisturizer",
    "description": "Buy the Olay HydraBoost Moisturizer from Olay. Moisturizer engineered for quality and value. Ideal for beauty needs.",
    "price": 11.46,
    "category": "Beauty",
    "rating": 3.9,
    "stock": 171,
    "brand": "Olay",
    "createdAt": "2025-05-17T07:30:55.802Z"
  },
  {
    "id": 53,
    "title": "Sony QLED Q80T 4K TV",
    "description": "Buy the Sony QLED Q80T 4K TV from Sony. 4K TV engineered for quality and value. Ideal for electronics needs.",
    "price": 1724.6,
    "category": "Electronics",
    "rating": 4.2,
    "stock": 249,
    "brand": "Sony",
    "createdAt": "2025-05-26T17:33:14.628Z"
  },
  {
    "id": 54,
    "title": "ASICS ZoomX Running Shoes",
    "description": "Buy the ASICS ZoomX Running Shoes from ASICS. Running Shoes engineered for quality and value. Ideal for sports needs.",
    "price": 141.88,
    "category": "Sports",
    "rating": 4.2,
    "stock": 301,
    "brand": "ASICS",
    "createdAt": "2025-03-27T18:56:42.108Z"
  },
  {
    "id": 55,
    "title": "Nike Chuck Taylor Sneakers",
    "description": "Buy the Nike Chuck Taylor Sneakers from Nike. Sneakers engineered for quality and value. Ideal for clothing needs.",
    "price": 235.98,
    "category": "Clothing",
    "rating": 1.3,
    "stock": 375,
    "brand": "Nike",
    "createdAt": "2025-08-30T14:12:58.146Z"
  },
  {
    "id": 56,
    "title": "Mattel Hero Series Action Figure",
    "description": "Buy the Mattel Hero Series Action Figure from Mattel. Action Figure engineered for quality and value. Ideal for toys needs.",
    "price": 47.78,
    "category": "Toys",
    "rating": 3.5,
    "stock": 179,
    "brand": "Mattel",
    "createdAt": "2025-04-19T05:26:48.853Z"
  },
  {
    "id": 57,
    "title": "Dyson PowerSweep Vacuum Cleaner",
    "description": "Buy the Dyson PowerSweep Vacuum Cleaner from Dyson. Vacuum Cleaner engineered for quality and value. Ideal for home needs.",
    "price": 560.52,
    "category": "Home",
    "rating": 4.6,
    "stock": 347,
    "brand": "Dyson",
    "createdAt": "2025-11-19T11:41:42.972Z"
  },
  {
    "id": 58,
    "title": "Hasbro Mega Blocks Building Blocks",
    "description": "Buy the Hasbro Mega Blocks Building Blocks from Hasbro. Building Blocks engineered for quality and value. Ideal for toys needs.",
    "price": 193.39,
    "category": "Toys",
    "rating": 3.8,
    "stock": 2,
    "brand": "Hasbro",
    "createdAt": "2025-06-26T08:59:04.113Z"
  },
  {
    "id": 59,
    "title": "Samsung Watch Series 6 Smartwatch",
    "description": "Buy the Samsung Watch Series 6 Smartwatch from Samsung. Smartwatch engineered for quality and value. Ideal for electronics needs.",
    "price": 396.84,
    "category": "Electronics",
    "rating": 3.1,
    "stock": 209,
    "brand": "Samsung",
    "createdAt": "2025-09-06T18:45:55.405Z"
  },
  {
    "id": 60,
    "title": "Mega Bloks Mega Blocks Building Blocks",
    "description": "Buy the Mega Bloks Mega Blocks Building Blocks from Mega Bloks. Building Blocks engineered for quality and value. Ideal for toys needs.",
    "price": 104.65,
    "category": "Toys",
    "rating": 1.8,
    "stock": 137,
    "brand": "Mega Bloks",
    "createdAt": "2025-05-18T16:35:27.026Z"
  },
  {
    "id": 61,
    "title": "Maybelline Satin Lipstick",
    "description": "Buy the Maybelline Satin Lipstick from Maybelline. Lipstick engineered for quality and value. Ideal for beauty needs.",
    "price": 17.48,
    "category": "Beauty",
    "rating": 5,
    "stock": 434,
    "brand": "Maybelline",
    "createdAt": "2025-03-20T13:19:56.246Z"
  },
  {
    "id": 62,
    "title": "Wrangler Straight Leg Jeans",
    "description": "Buy the Wrangler Straight Leg Jeans from Wrangler. Jeans engineered for quality and value. Ideal for clothing needs.",
    "price": 126.27,
    "category": "Clothing",
    "rating": 4.2,
    "stock": 422,
    "brand": "Wrangler",
    "createdAt": "2025-04-21T17:20:27.538Z"
  },
  {
    "id": 63,
    "title": "Manduka ProGrip Yoga Mat",
    "description": "Buy the Manduka ProGrip Yoga Mat from Manduka. Yoga Mat engineered for quality and value. Ideal for sports needs.",
    "price": 97.91,
    "category": "Sports",
    "rating": 1.8,
    "stock": 421,
    "brand": "Manduka",
    "createdAt": "2025-09-05T17:35:38.409Z"
  },
  {
    "id": 64,
    "title": "Neutrogena Daily Cream Moisturizer",
    "description": "Buy the Neutrogena Daily Cream Moisturizer from Neutrogena. Moisturizer engineered for quality and value. Ideal for beauty needs.",
    "price": 37.95,
    "category": "Beauty",
    "rating": 4.9,
    "stock": 316,
    "brand": "Neutrogena",
    "createdAt": "2025-06-24T23:17:30.315Z"
  },
  {
    "id": 65,
    "title": "HarperCollins Atomic Habits Non-Fiction",
    "description": "Buy the HarperCollins Atomic Habits Non-Fiction from HarperCollins. Non-Fiction engineered for quality and value. Ideal for books needs.",
    "price": 42.26,
    "category": "Books",
    "rating": 1.4,
    "stock": 130,
    "brand": "HarperCollins",
    "createdAt": "2026-02-11T12:51:21.162Z"
  },
  {
    "id": 66,
    "title": "Apple MacBook Air Laptop",
    "description": "Buy the Apple MacBook Air Laptop from Apple. Laptop engineered for quality and value. Ideal for electronics needs.",
    "price": 914.86,
    "category": "Electronics",
    "rating": 1.6,
    "stock": 241,
    "brand": "Apple",
    "createdAt": "2026-02-04T05:35:04.019Z"
  },
  {
    "id": 67,
    "title": "Mattel Hero Series Action Figure",
    "description": "Buy the Mattel Hero Series Action Figure from Mattel. Action Figure engineered for quality and value. Ideal for toys needs.",
    "price": 22.17,
    "category": "Toys",
    "rating": 4.5,
    "stock": 449,
    "brand": "Mattel",
    "createdAt": "2025-08-10T08:39:13.762Z"
  },
  {
    "id": 68,
    "title": "Shark Cyclone 3000 Vacuum Cleaner",
    "description": "Buy the Shark Cyclone 3000 Vacuum Cleaner from Shark. Vacuum Cleaner engineered for quality and value. Ideal for home needs.",
    "price": 342.78,
    "category": "Home",
    "rating": 3.2,
    "stock": 340,
    "brand": "Shark",
    "createdAt": "2025-09-23T17:42:36.505Z"
  },
  {
    "id": 69,
    "title": "Random House The Silent Patient Fiction Book",
    "description": "Buy the Random House The Silent Patient Fiction Book from Random House. Fiction Book engineered for quality and value. Ideal for books needs.",
    "price": 20.57,
    "category": "Books",
    "rating": 1.3,
    "stock": 455,
    "brand": "Random House",
    "createdAt": "2026-01-21T14:58:11.474Z"
  },
  {
    "id": 70,
    "title": "KitchenAid SmoothieX Blender",
    "description": "Buy the KitchenAid SmoothieX Blender from KitchenAid. Blender engineered for quality and value. Ideal for home needs.",
    "price": 45.1,
    "category": "Home",
    "rating": 2.3,
    "stock": 414,
    "brand": "KitchenAid",
    "createdAt": "2025-09-07T13:05:37.685Z"
  },
  {
    "id": 71,
    "title": "Hasbro Galaxy Fighter Action Figure",
    "description": "Buy the Hasbro Galaxy Fighter Action Figure from Hasbro. Action Figure engineered for quality and value. Ideal for toys needs.",
    "price": 7.09,
    "category": "Toys",
    "rating": 3.7,
    "stock": 393,
    "brand": "Hasbro",
    "createdAt": "2025-09-30T09:52:12.056Z"
  },
  {
    "id": 72,
    "title": "New Balance Gel-Nimbus Running Shoes",
    "description": "Buy the New Balance Gel-Nimbus Running Shoes from New Balance. Running Shoes engineered for quality and value. Ideal for sports needs.",
    "price": 191.14,
    "category": "Sports",
    "rating": 2.4,
    "stock": 459,
    "brand": "New Balance",
    "createdAt": "2025-12-27T02:21:09.832Z"
  },
  {
    "id": 73,
    "title": "Asus ThinkPad X1 Laptop",
    "description": "Buy the Asus ThinkPad X1 Laptop from Asus. Laptop engineered for quality and value. Ideal for electronics needs.",
    "price": 1973.63,
    "category": "Electronics",
    "rating": 3,
    "stock": 391,
    "brand": "Asus",
    "createdAt": "2025-10-02T08:40:50.064Z"
  },
  {
    "id": 74,
    "title": "Adidas Chuck Taylor Sneakers",
    "description": "Buy the Adidas Chuck Taylor Sneakers from Adidas. Sneakers engineered for quality and value. Ideal for clothing needs.",
    "price": 233.24,
    "category": "Clothing",
    "rating": 4.3,
    "stock": 263,
    "brand": "Adidas",
    "createdAt": "2025-08-23T05:37:14.389Z"
  },
  {
    "id": 75,
    "title": "Apple Galaxy S21 Smartphone",
    "description": "Buy the Apple Galaxy S21 Smartphone from Apple. Smartphone engineered for quality and value. Ideal for electronics needs.",
    "price": 291.77,
    "category": "Electronics",
    "rating": 1.7,
    "stock": 460,
    "brand": "Apple",
    "createdAt": "2025-06-29T20:06:24.197Z"
  },
  {
    "id": 76,
    "title": "Shark PowerSweep Vacuum Cleaner",
    "description": "Buy the Shark PowerSweep Vacuum Cleaner from Shark. Vacuum Cleaner engineered for quality and value. Ideal for home needs.",
    "price": 317.5,
    "category": "Home",
    "rating": 4.6,
    "stock": 48,
    "brand": "Shark",
    "createdAt": "2025-09-05T10:32:02.894Z"
  },
  {
    "id": 77,
    "title": "Neutrogena Daily Cream Moisturizer",
    "description": "Buy the Neutrogena Daily Cream Moisturizer from Neutrogena. Moisturizer engineered for quality and value. Ideal for beauty needs.",
    "price": 19.57,
    "category": "Beauty",
    "rating": 4.3,
    "stock": 20,
    "brand": "Neutrogena",
    "createdAt": "2025-04-17T19:22:59.981Z"
  },
  {
    "id": 78,
    "title": "Maybelline Matte Lipstick",
    "description": "Buy the Maybelline Matte Lipstick from Maybelline. Lipstick engineered for quality and value. Ideal for beauty needs.",
    "price": 3.49,
    "category": "Beauty",
    "rating": 3.6,
    "stock": 138,
    "brand": "Maybelline",
    "createdAt": "2025-10-08T07:42:42.110Z"
  },
  {
    "id": 79,
    "title": "KitchenAid SmoothieX Blender",
    "description": "Buy the KitchenAid SmoothieX Blender from KitchenAid. Blender engineered for quality and value. Ideal for home needs.",
    "price": 395.57,
    "category": "Home",
    "rating": 1.1,
    "stock": 36,
    "brand": "KitchenAid",
    "createdAt": "2025-04-11T10:38:26.124Z"
  },
  {
    "id": 80,
    "title": "Dyson PowerSweep Vacuum Cleaner",
    "description": "Buy the Dyson PowerSweep Vacuum Cleaner from Dyson. Vacuum Cleaner engineered for quality and value. Ideal for home needs.",
    "price": 436.68,
    "category": "Home",
    "rating": 3.8,
    "stock": 164,
    "brand": "Dyson",
    "createdAt": "2025-10-29T17:35:45.559Z"
  },
  {
    "id": 81,
    "title": "Neutrogena Daily Cream Moisturizer",
    "description": "Buy the Neutrogena Daily Cream Moisturizer from Neutrogena. Moisturizer engineered for quality and value. Ideal for beauty needs.",
    "price": 53.29,
    "category": "Beauty",
    "rating": 4.7,
    "stock": 362,
    "brand": "Neutrogena",
    "createdAt": "2026-01-19T06:15:11.434Z"
  },
  {
    "id": 82,
    "title": "Neutrogena HydraBoost Moisturizer",
    "description": "Buy the Neutrogena HydraBoost Moisturizer from Neutrogena. Moisturizer engineered for quality and value. Ideal for beauty needs.",
    "price": 72.76,
    "category": "Beauty",
    "rating": 3.6,
    "stock": 55,
    "brand": "Neutrogena",
    "createdAt": "2026-01-11T23:27:47.682Z"
  },
  {
    "id": 83,
    "title": "Hoover PowerSweep Vacuum Cleaner",
    "description": "Buy the Hoover PowerSweep Vacuum Cleaner from Hoover. Vacuum Cleaner engineered for quality and value. Ideal for home needs.",
    "price": 171.79,
    "category": "Home",
    "rating": 2.7,
    "stock": 304,
    "brand": "Hoover",
    "createdAt": "2025-11-05T14:08:20.788Z"
  },
  {
    "id": 84,
    "title": "Uniqlo Polo T-Shirt",
    "description": "Buy the Uniqlo Polo T-Shirt from Uniqlo. T-Shirt engineered for quality and value. Ideal for clothing needs.",
    "price": 35.47,
    "category": "Clothing",
    "rating": 3.4,
    "stock": 166,
    "brand": "Uniqlo",
    "createdAt": "2025-03-28T09:14:09.595Z"
  },
  {
    "id": 85,
    "title": "Mega Bloks Mega Blocks Building Blocks",
    "description": "Buy the Mega Bloks Mega Blocks Building Blocks from Mega Bloks. Building Blocks engineered for quality and value. Ideal for toys needs.",
    "price": 135.88,
    "category": "Toys",
    "rating": 1.2,
    "stock": 278,
    "brand": "Mega Bloks",
    "createdAt": "2025-09-25T18:14:25.139Z"
  },
  {
    "id": 86,
    "title": "Decathlon ProGrip Yoga Mat",
    "description": "Buy the Decathlon ProGrip Yoga Mat from Decathlon. Yoga Mat engineered for quality and value. Ideal for sports needs.",
    "price": 113.85,
    "category": "Sports",
    "rating": 2.1,
    "stock": 321,
    "brand": "Decathlon",
    "createdAt": "2026-03-12T15:34:16.450Z"
  },
  {
    "id": 87,
    "title": "Nike Gel-Nimbus Running Shoes",
    "description": "Buy the Nike Gel-Nimbus Running Shoes from Nike. Running Shoes engineered for quality and value. Ideal for sports needs.",
    "price": 209.49,
    "category": "Sports",
    "rating": 5,
    "stock": 466,
    "brand": "Nike",
    "createdAt": "2025-10-05T16:45:56.574Z"
  },
  {
    "id": 88,
    "title": "Bose QC35 II Wireless Headphones",
    "description": "Buy the Bose QC35 II Wireless Headphones from Bose. Wireless Headphones engineered for quality and value. Ideal for electronics needs.",
    "price": 256.86,
    "category": "Electronics",
    "rating": 4.9,
    "stock": 212,
    "brand": "Bose",
    "createdAt": "2025-07-25T09:59:35.062Z"
  },
  {
    "id": 89,
    "title": "Nike ZoomX Running Shoes",
    "description": "Buy the Nike ZoomX Running Shoes from Nike. Running Shoes engineered for quality and value. Ideal for sports needs.",
    "price": 150.33,
    "category": "Sports",
    "rating": 3.5,
    "stock": 378,
    "brand": "Nike",
    "createdAt": "2025-07-21T20:58:19.984Z"
  },
  {
    "id": 90,
    "title": "Manduka EcoMat Yoga Mat",
    "description": "Buy the Manduka EcoMat Yoga Mat from Manduka. Yoga Mat engineered for quality and value. Ideal for sports needs.",
    "price": 101.22,
    "category": "Sports",
    "rating": 1.6,
    "stock": 77,
    "brand": "Manduka",
    "createdAt": "2025-07-07T00:40:46.182Z"
  },
  {
    "id": 91,
    "title": "Lenovo ThinkPad X1 Laptop",
    "description": "Buy the Lenovo ThinkPad X1 Laptop from Lenovo. Laptop engineered for quality and value. Ideal for electronics needs.",
    "price": 570.08,
    "category": "Electronics",
    "rating": 5,
    "stock": 76,
    "brand": "Lenovo",
    "createdAt": "2025-07-01T08:42:28.299Z"
  },
  {
    "id": 92,
    "title": "Dyson PowerSweep Vacuum Cleaner",
    "description": "Buy the Dyson PowerSweep Vacuum Cleaner from Dyson. Vacuum Cleaner engineered for quality and value. Ideal for home needs.",
    "price": 455.61,
    "category": "Home",
    "rating": 2.1,
    "stock": 326,
    "brand": "Dyson",
    "createdAt": "2025-03-21T08:00:21.928Z"
  },
  {
    "id": 93,
    "title": "W.W. Norton Sapiens Non-Fiction",
    "description": "Buy the W.W. Norton Sapiens Non-Fiction from W.W. Norton. Non-Fiction engineered for quality and value. Ideal for books needs.",
    "price": 39.71,
    "category": "Books",
    "rating": 4,
    "stock": 309,
    "brand": "W.W. Norton",
    "createdAt": "2025-12-18T20:41:52.646Z"
  },
  {
    "id": 94,
    "title": "Manduka ProGrip Yoga Mat",
    "description": "Buy the Manduka ProGrip Yoga Mat from Manduka. Yoga Mat engineered for quality and value. Ideal for sports needs.",
    "price": 122.3,
    "category": "Sports",
    "rating": 1.7,
    "stock": 78,
    "brand": "Manduka",
    "createdAt": "2025-08-23T23:34:15.567Z"
  },
  {
    "id": 95,
    "title": "HarperCollins Sapiens Non-Fiction",
    "description": "Buy the HarperCollins Sapiens Non-Fiction from HarperCollins. Non-Fiction engineered for quality and value. Ideal for books needs.",
    "price": 35.46,
    "category": "Books",
    "rating": 2,
    "stock": 79,
    "brand": "HarperCollins",
    "createdAt": "2025-03-26T10:17:43.582Z"
  },
  {
    "id": 96,
    "title": "Dyson Cyclone 3000 Vacuum Cleaner",
    "description": "Buy the Dyson Cyclone 3000 Vacuum Cleaner from Dyson. Vacuum Cleaner engineered for quality and value. Ideal for home needs.",
    "price": 473.11,
    "category": "Home",
    "rating": 2.6,
    "stock": 324,
    "brand": "Dyson",
    "createdAt": "2025-05-20T14:03:49.724Z"
  },
  {
    "id": 97,
    "title": "Lululemon EcoMat Yoga Mat",
    "description": "Buy the Lululemon EcoMat Yoga Mat from Lululemon. Yoga Mat engineered for quality and value. Ideal for sports needs.",
    "price": 70.9,
    "category": "Sports",
    "rating": 4,
    "stock": 265,
    "brand": "Lululemon",
    "createdAt": "2025-11-22T22:15:06.998Z"
  },
  {
    "id": 98,
    "title": "Mattel Galaxy Fighter Action Figure",
    "description": "Buy the Mattel Galaxy Fighter Action Figure from Mattel. Action Figure engineered for quality and value. Ideal for toys needs.",
    "price": 13.09,
    "category": "Toys",
    "rating": 1.7,
    "stock": 179,
    "brand": "Mattel",
    "createdAt": "2025-04-18T07:09:27.970Z"
  },
  {
    "id": 99,
    "title": "Random House The Last Kingdom Fiction Book",
    "description": "Buy the Random House The Last Kingdom Fiction Book from Random House. Fiction Book engineered for quality and value. Ideal for books needs.",
    "price": 31.03,
    "category": "Books",
    "rating": 1.2,
    "stock": 94,
    "brand": "Random House",
    "createdAt": "2025-08-27T08:50:39.000Z"
  },
  {
    "id": 100,
    "title": "Dyson PowerSweep Vacuum Cleaner",
    "description": "Buy the Dyson PowerSweep Vacuum Cleaner from Dyson. Vacuum Cleaner engineered for quality and value. Ideal for home needs.",
    "price": 370.49,
    "category": "Home",
    "rating": 1.2,
    "stock": 3,
    "brand": "Dyson",
    "createdAt": "2025-06-23T12:41:16.975Z"
  },
  {
    "id": 101,
    "title": "HarperCollins The Silent Patient Fiction Book",
    "description": "Buy the HarperCollins The Silent Patient Fiction Book from HarperCollins. Fiction Book engineered for quality and value. Ideal for books needs.",
    "price": 27.96,
    "category": "Books",
    "rating": 4.9,
    "stock": 92,
    "brand": "HarperCollins",
    "createdAt": "2025-04-28T05:05:10.021Z"
  },
  {
    "id": 102,
    "title": "HarperCollins Sapiens Non-Fiction",
    "description": "Buy the HarperCollins Sapiens Non-Fiction from HarperCollins. Non-Fiction engineered for quality and value. Ideal for books needs.",
    "price": 7.3,
    "category": "Books",
    "rating": 1,
    "stock": 406,
    "brand": "HarperCollins",
    "createdAt": "2025-09-27T14:13:44.762Z"
  },
  {
    "id": 103,
    "title": "Cetaphil Daily Cream Moisturizer",
    "description": "Buy the Cetaphil Daily Cream Moisturizer from Cetaphil. Moisturizer engineered for quality and value. Ideal for beauty needs.",
    "price": 5.01,
    "category": "Beauty",
    "rating": 2.1,
    "stock": 189,
    "brand": "Cetaphil",
    "createdAt": "2025-09-04T15:15:17.547Z"
  },
  {
    "id": 104,
    "title": "Google Galaxy Watch 4 Smartwatch",
    "description": "Buy the Google Galaxy Watch 4 Smartwatch from Google. Smartwatch engineered for quality and value. Ideal for electronics needs.",
    "price": 206.06,
    "category": "Electronics",
    "rating": 4.9,
    "stock": 413,
    "brand": "Google",
    "createdAt": "2025-06-12T15:43:37.059Z"
  },
  {
    "id": 105,
    "title": "Mattel Galaxy Fighter Action Figure",
    "description": "Buy the Mattel Galaxy Fighter Action Figure from Mattel. Action Figure engineered for quality and value. Ideal for toys needs.",
    "price": 8.54,
    "category": "Toys",
    "rating": 2.8,
    "stock": 163,
    "brand": "Mattel",
    "createdAt": "2025-10-20T23:11:55.435Z"
  },
  {
    "id": 106,
    "title": "LG Bravia X90J 4K TV",
    "description": "Buy the LG Bravia X90J 4K TV from LG. 4K TV engineered for quality and value. Ideal for electronics needs.",
    "price": 1377.19,
    "category": "Electronics",
    "rating": 1.4,
    "stock": 202,
    "brand": "LG",
    "createdAt": "2025-11-11T03:37:11.196Z"
  },
  {
    "id": 107,
    "title": "Neutrogena HydraBoost Moisturizer",
    "description": "Buy the Neutrogena HydraBoost Moisturizer from Neutrogena. Moisturizer engineered for quality and value. Ideal for beauty needs.",
    "price": 73.02,
    "category": "Beauty",
    "rating": 3.4,
    "stock": 491,
    "brand": "Neutrogena",
    "createdAt": "2025-11-26T09:52:14.654Z"
  },
  {
    "id": 108,
    "title": "Hasbro Galaxy Fighter Action Figure",
    "description": "Buy the Hasbro Galaxy Fighter Action Figure from Hasbro. Action Figure engineered for quality and value. Ideal for toys needs.",
    "price": 77.28,
    "category": "Toys",
    "rating": 3,
    "stock": 213,
    "brand": "Hasbro",
    "createdAt": "2025-07-04T14:54:48.645Z"
  },
  {
    "id": 109,
    "title": "Olay HydraBoost Moisturizer",
    "description": "Buy the Olay HydraBoost Moisturizer from Olay. Moisturizer engineered for quality and value. Ideal for beauty needs.",
    "price": 72.42,
    "category": "Beauty",
    "rating": 4.1,
    "stock": 40,
    "brand": "Olay",
    "createdAt": "2025-07-10T10:47:17.042Z"
  },
  {
    "id": 110,
    "title": "Olay HydraBoost Moisturizer",
    "description": "Buy the Olay HydraBoost Moisturizer from Olay. Moisturizer engineered for quality and value. Ideal for beauty needs.",
    "price": 57.11,
    "category": "Beauty",
    "rating": 1.6,
    "stock": 363,
    "brand": "Olay",
    "createdAt": "2025-09-01T14:40:54.145Z"
  },
  {
    "id": 111,
    "title": "Apple MacBook Air Laptop",
    "description": "Buy the Apple MacBook Air Laptop from Apple. Laptop engineered for quality and value. Ideal for electronics needs.",
    "price": 1824.95,
    "category": "Electronics",
    "rating": 2.8,
    "stock": 429,
    "brand": "Apple",
    "createdAt": "2025-12-17T23:14:56.819Z"
  },
  {
    "id": 112,
    "title": "Decathlon EcoMat Yoga Mat",
    "description": "Buy the Decathlon EcoMat Yoga Mat from Decathlon. Yoga Mat engineered for quality and value. Ideal for sports needs.",
    "price": 65.76,
    "category": "Sports",
    "rating": 2.2,
    "stock": 201,
    "brand": "Decathlon",
    "createdAt": "2025-06-12T10:32:00.944Z"
  },
  {
    "id": 113,
    "title": "Philips SmoothieX Blender",
    "description": "Buy the Philips SmoothieX Blender from Philips. Blender engineered for quality and value. Ideal for home needs.",
    "price": 124.71,
    "category": "Home",
    "rating": 2.2,
    "stock": 142,
    "brand": "Philips",
    "createdAt": "2026-03-01T05:59:29.810Z"
  },
  {
    "id": 114,
    "title": "Random House The Last Kingdom Fiction Book",
    "description": "Buy the Random House The Last Kingdom Fiction Book from Random House. Fiction Book engineered for quality and value. Ideal for books needs.",
    "price": 25.43,
    "category": "Books",
    "rating": 2.1,
    "stock": 90,
    "brand": "Random House",
    "createdAt": "2025-08-05T18:02:43.867Z"
  },
  {
    "id": 115,
    "title": "L'Oreal Matte Lipstick",
    "description": "Buy the L'Oreal Matte Lipstick from L'Oreal. Lipstick engineered for quality and value. Ideal for beauty needs.",
    "price": 31.62,
    "category": "Beauty",
    "rating": 3.2,
    "stock": 306,
    "brand": "L'Oreal",
    "createdAt": "2025-09-15T06:46:25.602Z"
  },
  {
    "id": 116,
    "title": "New Balance Fresh Foam Running Shoes",
    "description": "Buy the New Balance Fresh Foam Running Shoes from New Balance. Running Shoes engineered for quality and value. Ideal for sports needs.",
    "price": 122.95,
    "category": "Sports",
    "rating": 1.4,
    "stock": 415,
    "brand": "New Balance",
    "createdAt": "2025-12-09T16:50:28.206Z"
  },
  {
    "id": 117,
    "title": "L'Oreal Satin Lipstick",
    "description": "Buy the L'Oreal Satin Lipstick from L'Oreal. Lipstick engineered for quality and value. Ideal for beauty needs.",
    "price": 15.56,
    "category": "Beauty",
    "rating": 3.8,
    "stock": 143,
    "brand": "L'Oreal",
    "createdAt": "2026-01-17T15:54:26.848Z"
  },
  {
    "id": 118,
    "title": "MAC Satin Lipstick",
    "description": "Buy the MAC Satin Lipstick from MAC. Lipstick engineered for quality and value. Ideal for beauty needs.",
    "price": 14.96,
    "category": "Beauty",
    "rating": 2.9,
    "stock": 484,
    "brand": "MAC",
    "createdAt": "2025-12-07T20:36:28.873Z"
  },
  {
    "id": 119,
    "title": "Ninja ProBlend Blender",
    "description": "Buy the Ninja ProBlend Blender from Ninja. Blender engineered for quality and value. Ideal for home needs.",
    "price": 317.73,
    "category": "Home",
    "rating": 1.5,
    "stock": 351,
    "brand": "Ninja",
    "createdAt": "2025-11-01T10:36:40.419Z"
  },
  {
    "id": 120,
    "title": "Sony QLED Q80T 4K TV",
    "description": "Buy the Sony QLED Q80T 4K TV from Sony. 4K TV engineered for quality and value. Ideal for electronics needs.",
    "price": 1153.47,
    "category": "Electronics",
    "rating": 2.1,
    "stock": 122,
    "brand": "Sony",
    "createdAt": "2025-12-06T23:58:12.178Z"
  },
  {
    "id": 121,
    "title": "Neutrogena HydraBoost Moisturizer",
    "description": "Buy the Neutrogena HydraBoost Moisturizer from Neutrogena. Moisturizer engineered for quality and value. Ideal for beauty needs.",
    "price": 52.78,
    "category": "Beauty",
    "rating": 4.8,
    "stock": 298,
    "brand": "Neutrogena",
    "createdAt": "2025-03-26T04:59:23.296Z"
  },
  {
    "id": 122,
    "title": "Samsung iPhone 12 Smartphone",
    "description": "Buy the Samsung iPhone 12 Smartphone from Samsung. Smartphone engineered for quality and value. Ideal for electronics needs.",
    "price": 437.81,
    "category": "Electronics",
    "rating": 4.9,
    "stock": 290,
    "brand": "Samsung",
    "createdAt": "2025-12-19T02:11:47.426Z"
  },
  {
    "id": 123,
    "title": "Adidas Ultraboost Sneakers",
    "description": "Buy the Adidas Ultraboost Sneakers from Adidas. Sneakers engineered for quality and value. Ideal for clothing needs.",
    "price": 47.56,
    "category": "Clothing",
    "rating": 2.9,
    "stock": 453,
    "brand": "Adidas",
    "createdAt": "2025-07-18T19:19:17.125Z"
  },
  {
    "id": 124,
    "title": "Neutrogena HydraBoost Moisturizer",
    "description": "Buy the Neutrogena HydraBoost Moisturizer from Neutrogena. Moisturizer engineered for quality and value. Ideal for beauty needs.",
    "price": 46.68,
    "category": "Beauty",
    "rating": 3.5,
    "stock": 51,
    "brand": "Neutrogena",
    "createdAt": "2025-04-17T16:16:17.038Z"
  },
  {
    "id": 125,
    "title": "Levi's Classic Tee T-Shirt",
    "description": "Buy the Levi's Classic Tee T-Shirt from Levi's. T-Shirt engineered for quality and value. Ideal for clothing needs.",
    "price": 22.66,
    "category": "Clothing",
    "rating": 1.2,
    "stock": 167,
    "brand": "Levi's",
    "createdAt": "2025-09-23T12:23:30.835Z"
  },
  {
    "id": 126,
    "title": "LEGO Mega Blocks Building Blocks",
    "description": "Buy the LEGO Mega Blocks Building Blocks from LEGO. Building Blocks engineered for quality and value. Ideal for toys needs.",
    "price": 131.23,
    "category": "Toys",
    "rating": 3.7,
    "stock": 206,
    "brand": "LEGO",
    "createdAt": "2026-01-22T21:55:24.371Z"
  },
  {
    "id": 127,
    "title": "Apple ZenBook 14 Laptop",
    "description": "Buy the Apple ZenBook 14 Laptop from Apple. Laptop engineered for quality and value. Ideal for electronics needs.",
    "price": 1523.09,
    "category": "Electronics",
    "rating": 3.9,
    "stock": 10,
    "brand": "Apple",
    "createdAt": "2025-03-29T00:19:11.469Z"
  },
  {
    "id": 128,
    "title": "Hasbro Galaxy Fighter Action Figure",
    "description": "Buy the Hasbro Galaxy Fighter Action Figure from Hasbro. Action Figure engineered for quality and value. Ideal for toys needs.",
    "price": 23.74,
    "category": "Toys",
    "rating": 1.1,
    "stock": 289,
    "brand": "Hasbro",
    "createdAt": "2025-07-03T04:18:09.812Z"
  },
  {
    "id": 129,
    "title": "HarperCollins Educated Non-Fiction",
    "description": "Buy the HarperCollins Educated Non-Fiction from HarperCollins. Non-Fiction engineered for quality and value. Ideal for books needs.",
    "price": 11.17,
    "category": "Books",
    "rating": 1.1,
    "stock": 40,
    "brand": "HarperCollins",
    "createdAt": "2025-06-06T01:13:30.081Z"
  },
  {
    "id": 130,
    "title": "Mattel Hero Series Action Figure",
    "description": "Buy the Mattel Hero Series Action Figure from Mattel. Action Figure engineered for quality and value. Ideal for toys needs.",
    "price": 68.52,
    "category": "Toys",
    "rating": 4.3,
    "stock": 127,
    "brand": "Mattel",
    "createdAt": "2026-01-20T06:16:08.701Z"
  },
  {
    "id": 131,
    "title": "Manduka ProGrip Yoga Mat",
    "description": "Buy the Manduka ProGrip Yoga Mat from Manduka. Yoga Mat engineered for quality and value. Ideal for sports needs.",
    "price": 75.56,
    "category": "Sports",
    "rating": 2.1,
    "stock": 261,
    "brand": "Manduka",
    "createdAt": "2025-06-15T08:18:17.507Z"
  },
  {
    "id": 132,
    "title": "Mattel Galaxy Fighter Action Figure",
    "description": "Buy the Mattel Galaxy Fighter Action Figure from Mattel. Action Figure engineered for quality and value. Ideal for toys needs.",
    "price": 17.94,
    "category": "Toys",
    "rating": 3.1,
    "stock": 354,
    "brand": "Mattel",
    "createdAt": "2025-10-17T10:46:18.544Z"
  },
  {
    "id": 133,
    "title": "KitchenAid ProBlend Blender",
    "description": "Buy the KitchenAid ProBlend Blender from KitchenAid. Blender engineered for quality and value. Ideal for home needs.",
    "price": 68.59,
    "category": "Home",
    "rating": 4.8,
    "stock": 227,
    "brand": "KitchenAid",
    "createdAt": "2025-03-20T18:05:16.819Z"
  },
  {
    "id": 134,
    "title": "Olay Daily Cream Moisturizer",
    "description": "Buy the Olay Daily Cream Moisturizer from Olay. Moisturizer engineered for quality and value. Ideal for beauty needs.",
    "price": 76.05,
    "category": "Beauty",
    "rating": 2.4,
    "stock": 371,
    "brand": "Olay",
    "createdAt": "2025-04-22T02:15:02.082Z"
  },
  {
    "id": 135,
    "title": "New Balance Fresh Foam Running Shoes",
    "description": "Buy the New Balance Fresh Foam Running Shoes from New Balance. Running Shoes engineered for quality and value. Ideal for sports needs.",
    "price": 208.38,
    "category": "Sports",
    "rating": 1.4,
    "stock": 112,
    "brand": "New Balance",
    "createdAt": "2025-08-13T13:38:42.869Z"
  },
  {
    "id": 136,
    "title": "W.W. Norton Sapiens Non-Fiction",
    "description": "Buy the W.W. Norton Sapiens Non-Fiction from W.W. Norton. Non-Fiction engineered for quality and value. Ideal for books needs.",
    "price": 15.38,
    "category": "Books",
    "rating": 3.5,
    "stock": 435,
    "brand": "W.W. Norton",
    "createdAt": "2025-10-02T16:49:02.575Z"
  },
  {
    "id": 137,
    "title": "Lululemon EcoMat Yoga Mat",
    "description": "Buy the Lululemon EcoMat Yoga Mat from Lululemon. Yoga Mat engineered for quality and value. Ideal for sports needs.",
    "price": 28.32,
    "category": "Sports",
    "rating": 3.9,
    "stock": 202,
    "brand": "Lululemon",
    "createdAt": "2025-10-31T01:51:27.592Z"
  },
  {
    "id": 138,
    "title": "Random House Midnight Library Fiction Book",
    "description": "Buy the Random House Midnight Library Fiction Book from Random House. Fiction Book engineered for quality and value. Ideal for books needs.",
    "price": 32.44,
    "category": "Books",
    "rating": 3.7,
    "stock": 179,
    "brand": "Random House",
    "createdAt": "2025-07-18T20:35:01.354Z"
  },
  {
    "id": 139,
    "title": "Manduka EcoMat Yoga Mat",
    "description": "Buy the Manduka EcoMat Yoga Mat from Manduka. Yoga Mat engineered for quality and value. Ideal for sports needs.",
    "price": 93.55,
    "category": "Sports",
    "rating": 2.1,
    "stock": 467,
    "brand": "Manduka",
    "createdAt": "2025-06-26T21:09:07.665Z"
  },
  {
    "id": 140,
    "title": "H&M Polo T-Shirt",
    "description": "Buy the H&M Polo T-Shirt from H&M. T-Shirt engineered for quality and value. Ideal for clothing needs.",
    "price": 72.07,
    "category": "Clothing",
    "rating": 2.5,
    "stock": 285,
    "brand": "H&M",
    "createdAt": "2025-08-14T14:38:27.782Z"
  },
  {
    "id": 141,
    "title": "LEGO Classic Bricks Building Blocks",
    "description": "Buy the LEGO Classic Bricks Building Blocks from LEGO. Building Blocks engineered for quality and value. Ideal for toys needs.",
    "price": 24.2,
    "category": "Toys",
    "rating": 4.4,
    "stock": 293,
    "brand": "LEGO",
    "createdAt": "2025-08-07T17:18:47.413Z"
  },
  {
    "id": 142,
    "title": "Apple Galaxy Watch 4 Smartwatch",
    "description": "Buy the Apple Galaxy Watch 4 Smartwatch from Apple. Smartwatch engineered for quality and value. Ideal for electronics needs.",
    "price": 682.24,
    "category": "Electronics",
    "rating": 3.6,
    "stock": 248,
    "brand": "Apple",
    "createdAt": "2026-03-09T22:49:06.723Z"
  },
  {
    "id": 143,
    "title": "Google Watch Series 6 Smartwatch",
    "description": "Buy the Google Watch Series 6 Smartwatch from Google. Smartwatch engineered for quality and value. Ideal for electronics needs.",
    "price": 335.63,
    "category": "Electronics",
    "rating": 1.6,
    "stock": 222,
    "brand": "Google",
    "createdAt": "2025-09-07T06:28:05.097Z"
  },
  {
    "id": 144,
    "title": "Manduka ProGrip Yoga Mat",
    "description": "Buy the Manduka ProGrip Yoga Mat from Manduka. Yoga Mat engineered for quality and value. Ideal for sports needs.",
    "price": 118.1,
    "category": "Sports",
    "rating": 1.1,
    "stock": 257,
    "brand": "Manduka",
    "createdAt": "2025-07-04T01:38:54.803Z"
  },
  {
    "id": 145,
    "title": "Samsung iPhone 12 Smartphone",
    "description": "Buy the Samsung iPhone 12 Smartphone from Samsung. Smartphone engineered for quality and value. Ideal for electronics needs.",
    "price": 972.79,
    "category": "Electronics",
    "rating": 3.1,
    "stock": 329,
    "brand": "Samsung",
    "createdAt": "2025-12-15T07:38:30.468Z"
  },
  {
    "id": 146,
    "title": "Hoover Cyclone 3000 Vacuum Cleaner",
    "description": "Buy the Hoover Cyclone 3000 Vacuum Cleaner from Hoover. Vacuum Cleaner engineered for quality and value. Ideal for home needs.",
    "price": 538.01,
    "category": "Home",
    "rating": 4.8,
    "stock": 487,
    "brand": "Hoover",
    "createdAt": "2026-02-03T22:42:56.434Z"
  },
  {
    "id": 147,
    "title": "Neutrogena Daily Cream Moisturizer",
    "description": "Buy the Neutrogena Daily Cream Moisturizer from Neutrogena. Moisturizer engineered for quality and value. Ideal for beauty needs.",
    "price": 62.28,
    "category": "Beauty",
    "rating": 2.9,
    "stock": 175,
    "brand": "Neutrogena",
    "createdAt": "2026-01-31T13:35:09.799Z"
  },
  {
    "id": 148,
    "title": "Lenovo MacBook Air Laptop",
    "description": "Buy the Lenovo MacBook Air Laptop from Lenovo. Laptop engineered for quality and value. Ideal for electronics needs.",
    "price": 2351.21,
    "category": "Electronics",
    "rating": 4.7,
    "stock": 242,
    "brand": "Lenovo",
    "createdAt": "2026-01-21T16:16:11.532Z"
  },
  {
    "id": 149,
    "title": "L'Oreal Satin Lipstick",
    "description": "Buy the L'Oreal Satin Lipstick from L'Oreal. Lipstick engineered for quality and value. Ideal for beauty needs.",
    "price": 34.14,
    "category": "Beauty",
    "rating": 1.5,
    "stock": 16,
    "brand": "L'Oreal",
    "createdAt": "2025-04-14T18:29:09.855Z"
  },
  {
    "id": 150,
    "title": "Wrangler Straight Leg Jeans",
    "description": "Buy the Wrangler Straight Leg Jeans from Wrangler. Jeans engineered for quality and value. Ideal for clothing needs.",
    "price": 117.61,
    "category": "Clothing",
    "rating": 4.6,
    "stock": 25,
    "brand": "Wrangler",
    "createdAt": "2026-03-06T20:25:24.811Z"
  },
  {
    "id": 151,
    "title": "Nike Ultraboost Sneakers",
    "description": "Buy the Nike Ultraboost Sneakers from Nike. Sneakers engineered for quality and value. Ideal for clothing needs.",
    "price": 212.51,
    "category": "Clothing",
    "rating": 1.1,
    "stock": 2,
    "brand": "Nike",
    "createdAt": "2026-02-20T05:09:46.586Z"
  },
  {
    "id": 152,
    "title": "Penguin Atomic Habits Non-Fiction",
    "description": "Buy the Penguin Atomic Habits Non-Fiction from Penguin. Non-Fiction engineered for quality and value. Ideal for books needs.",
    "price": 16.04,
    "category": "Books",
    "rating": 1.9,
    "stock": 88,
    "brand": "Penguin",
    "createdAt": "2025-08-31T05:00:05.452Z"
  },
  {
    "id": 153,
    "title": "Philips ProBlend Blender",
    "description": "Buy the Philips ProBlend Blender from Philips. Blender engineered for quality and value. Ideal for home needs.",
    "price": 138.05,
    "category": "Home",
    "rating": 2.8,
    "stock": 48,
    "brand": "Philips",
    "createdAt": "2025-10-31T01:42:53.217Z"
  },
  {
    "id": 154,
    "title": "Cetaphil HydraBoost Moisturizer",
    "description": "Buy the Cetaphil HydraBoost Moisturizer from Cetaphil. Moisturizer engineered for quality and value. Ideal for beauty needs.",
    "price": 56.26,
    "category": "Beauty",
    "rating": 3.4,
    "stock": 384,
    "brand": "Cetaphil",
    "createdAt": "2025-12-12T08:30:41.015Z"
  },
  {
    "id": 155,
    "title": "Converse Air Max Sneakers",
    "description": "Buy the Converse Air Max Sneakers from Converse. Sneakers engineered for quality and value. Ideal for clothing needs.",
    "price": 131.3,
    "category": "Clothing",
    "rating": 2.4,
    "stock": 357,
    "brand": "Converse",
    "createdAt": "2025-05-12T21:22:38.340Z"
  },
  {
    "id": 156,
    "title": "W.W. Norton Educated Non-Fiction",
    "description": "Buy the W.W. Norton Educated Non-Fiction from W.W. Norton. Non-Fiction engineered for quality and value. Ideal for books needs.",
    "price": 26.85,
    "category": "Books",
    "rating": 2.5,
    "stock": 183,
    "brand": "W.W. Norton",
    "createdAt": "2025-10-24T06:32:44.560Z"
  },
  {
    "id": 157,
    "title": "Apple iPhone 12 Smartphone",
    "description": "Buy the Apple iPhone 12 Smartphone from Apple. Smartphone engineered for quality and value. Ideal for electronics needs.",
    "price": 627.4,
    "category": "Electronics",
    "rating": 4.8,
    "stock": 371,
    "brand": "Apple",
    "createdAt": "2025-08-06T05:45:14.134Z"
  },
  {
    "id": 158,
    "title": "Sony Bravia X90J 4K TV",
    "description": "Buy the Sony Bravia X90J 4K TV from Sony. 4K TV engineered for quality and value. Ideal for electronics needs.",
    "price": 2205.6,
    "category": "Electronics",
    "rating": 3.3,
    "stock": 135,
    "brand": "Sony",
    "createdAt": "2025-05-09T08:37:16.068Z"
  },
  {
    "id": 159,
    "title": "Olay Daily Cream Moisturizer",
    "description": "Buy the Olay Daily Cream Moisturizer from Olay. Moisturizer engineered for quality and value. Ideal for beauty needs.",
    "price": 45.19,
    "category": "Beauty",
    "rating": 1.9,
    "stock": 104,
    "brand": "Olay",
    "createdAt": "2026-03-08T01:10:23.154Z"
  },
  {
    "id": 160,
    "title": "Ninja SmoothieX Blender",
    "description": "Buy the Ninja SmoothieX Blender from Ninja. Blender engineered for quality and value. Ideal for home needs.",
    "price": 83.54,
    "category": "Home",
    "rating": 1.1,
    "stock": 61,
    "brand": "Ninja",
    "createdAt": "2025-05-23T16:32:24.156Z"
  },
  {
    "id": 161,
    "title": "Hasbro Hero Series Action Figure",
    "description": "Buy the Hasbro Hero Series Action Figure from Hasbro. Action Figure engineered for quality and value. Ideal for toys needs.",
    "price": 34.09,
    "category": "Toys",
    "rating": 1.6,
    "stock": 480,
    "brand": "Hasbro",
    "createdAt": "2025-11-07T06:28:11.155Z"
  },
  {
    "id": 162,
    "title": "Bose WH-1000XM4 Wireless Headphones",
    "description": "Buy the Bose WH-1000XM4 Wireless Headphones from Bose. Wireless Headphones engineered for quality and value. Ideal for electronics needs.",
    "price": 331.11,
    "category": "Electronics",
    "rating": 1.3,
    "stock": 221,
    "brand": "Bose",
    "createdAt": "2025-07-10T03:36:03.801Z"
  },
  {
    "id": 163,
    "title": "New Balance Fresh Foam Running Shoes",
    "description": "Buy the New Balance Fresh Foam Running Shoes from New Balance. Running Shoes engineered for quality and value. Ideal for sports needs.",
    "price": 241.44,
    "category": "Sports",
    "rating": 3.8,
    "stock": 476,
    "brand": "New Balance",
    "createdAt": "2025-12-12T03:24:37.738Z"
  },
  {
    "id": 164,
    "title": "Mattel Hero Series Action Figure",
    "description": "Buy the Mattel Hero Series Action Figure from Mattel. Action Figure engineered for quality and value. Ideal for toys needs.",
    "price": 11.18,
    "category": "Toys",
    "rating": 1.1,
    "stock": 62,
    "brand": "Mattel",
    "createdAt": "2025-12-20T14:40:53.942Z"
  },
  {
    "id": 165,
    "title": "Converse Ultraboost Sneakers",
    "description": "Buy the Converse Ultraboost Sneakers from Converse. Sneakers engineered for quality and value. Ideal for clothing needs.",
    "price": 90.8,
    "category": "Clothing",
    "rating": 3.6,
    "stock": 68,
    "brand": "Converse",
    "createdAt": "2025-06-02T09:40:21.801Z"
  },
  {
    "id": 166,
    "title": "Nike Ultraboost Sneakers",
    "description": "Buy the Nike Ultraboost Sneakers from Nike. Sneakers engineered for quality and value. Ideal for clothing needs.",
    "price": 225.04,
    "category": "Clothing",
    "rating": 2.5,
    "stock": 66,
    "brand": "Nike",
    "createdAt": "2025-05-31T16:20:17.527Z"
  },
  {
    "id": 167,
    "title": "Maybelline Satin Lipstick",
    "description": "Buy the Maybelline Satin Lipstick from Maybelline. Lipstick engineered for quality and value. Ideal for beauty needs.",
    "price": 30.05,
    "category": "Beauty",
    "rating": 2.4,
    "stock": 227,
    "brand": "Maybelline",
    "createdAt": "2025-06-22T08:21:47.182Z"
  },
  {
    "id": 168,
    "title": "Apple ThinkPad X1 Laptop",
    "description": "Buy the Apple ThinkPad X1 Laptop from Apple. Laptop engineered for quality and value. Ideal for electronics needs.",
    "price": 1738.91,
    "category": "Electronics",
    "rating": 1.9,
    "stock": 357,
    "brand": "Apple",
    "createdAt": "2025-05-28T09:20:19.242Z"
  },
  {
    "id": 169,
    "title": "Penguin Atomic Habits Non-Fiction",
    "description": "Buy the Penguin Atomic Habits Non-Fiction from Penguin. Non-Fiction engineered for quality and value. Ideal for books needs.",
    "price": 17.24,
    "category": "Books",
    "rating": 2.3,
    "stock": 395,
    "brand": "Penguin",
    "createdAt": "2026-03-09T17:23:18.829Z"
  },
  {
    "id": 170,
    "title": "Mattel Hero Series Action Figure",
    "description": "Buy the Mattel Hero Series Action Figure from Mattel. Action Figure engineered for quality and value. Ideal for toys needs.",
    "price": 20.57,
    "category": "Toys",
    "rating": 2.7,
    "stock": 446,
    "brand": "Mattel",
    "createdAt": "2025-12-04T18:05:54.427Z"
  },
  {
    "id": 171,
    "title": "Apple ThinkPad X1 Laptop",
    "description": "Buy the Apple ThinkPad X1 Laptop from Apple. Laptop engineered for quality and value. Ideal for electronics needs.",
    "price": 1546.42,
    "category": "Electronics",
    "rating": 3.6,
    "stock": 30,
    "brand": "Apple",
    "createdAt": "2025-12-17T20:52:42.238Z"
  },
  {
    "id": 172,
    "title": "Penguin Sapiens Non-Fiction",
    "description": "Buy the Penguin Sapiens Non-Fiction from Penguin. Non-Fiction engineered for quality and value. Ideal for books needs.",
    "price": 10.2,
    "category": "Books",
    "rating": 1.6,
    "stock": 353,
    "brand": "Penguin",
    "createdAt": "2026-01-03T00:58:41.992Z"
  },
  {
    "id": 173,
    "title": "Mattel Galaxy Fighter Action Figure",
    "description": "Buy the Mattel Galaxy Fighter Action Figure from Mattel. Action Figure engineered for quality and value. Ideal for toys needs.",
    "price": 34.98,
    "category": "Toys",
    "rating": 4.7,
    "stock": 492,
    "brand": "Mattel",
    "createdAt": "2026-01-17T21:25:42.947Z"
  },
  {
    "id": 174,
    "title": "HarperCollins Midnight Library Fiction Book",
    "description": "Buy the HarperCollins Midnight Library Fiction Book from HarperCollins. Fiction Book engineered for quality and value. Ideal for books needs.",
    "price": 28.17,
    "category": "Books",
    "rating": 1.7,
    "stock": 372,
    "brand": "HarperCollins",
    "createdAt": "2026-01-13T12:36:33.088Z"
  },
  {
    "id": 175,
    "title": "Random House The Silent Patient Fiction Book",
    "description": "Buy the Random House The Silent Patient Fiction Book from Random House. Fiction Book engineered for quality and value. Ideal for books needs.",
    "price": 11.48,
    "category": "Books",
    "rating": 3.9,
    "stock": 456,
    "brand": "Random House",
    "createdAt": "2025-09-27T11:19:20.237Z"
  },
  {
    "id": 176,
    "title": "Dell MacBook Air Laptop",
    "description": "Buy the Dell MacBook Air Laptop from Dell. Laptop engineered for quality and value. Ideal for electronics needs.",
    "price": 676.93,
    "category": "Electronics",
    "rating": 2.5,
    "stock": 121,
    "brand": "Dell",
    "createdAt": "2025-09-20T01:51:47.403Z"
  },
  {
    "id": 177,
    "title": "Olay HydraBoost Moisturizer",
    "description": "Buy the Olay HydraBoost Moisturizer from Olay. Moisturizer engineered for quality and value. Ideal for beauty needs.",
    "price": 30.56,
    "category": "Beauty",
    "rating": 3.9,
    "stock": 31,
    "brand": "Olay",
    "createdAt": "2025-11-04T11:19:23.063Z"
  },
  {
    "id": 178,
    "title": "Neutrogena HydraBoost Moisturizer",
    "description": "Buy the Neutrogena HydraBoost Moisturizer from Neutrogena. Moisturizer engineered for quality and value. Ideal for beauty needs.",
    "price": 29.92,
    "category": "Beauty",
    "rating": 1.3,
    "stock": 360,
    "brand": "Neutrogena",
    "createdAt": "2026-03-15T17:25:38.630Z"
  },
  {
    "id": 179,
    "title": "Mattel Hero Series Action Figure",
    "description": "Buy the Mattel Hero Series Action Figure from Mattel. Action Figure engineered for quality and value. Ideal for toys needs.",
    "price": 34.48,
    "category": "Toys",
    "rating": 2.7,
    "stock": 323,
    "brand": "Mattel",
    "createdAt": "2025-11-11T03:25:21.238Z"
  },
  {
    "id": 180,
    "title": "W.W. Norton Atomic Habits Non-Fiction",
    "description": "Buy the W.W. Norton Atomic Habits Non-Fiction from W.W. Norton. Non-Fiction engineered for quality and value. Ideal for books needs.",
    "price": 26.64,
    "category": "Books",
    "rating": 2,
    "stock": 404,
    "brand": "W.W. Norton",
    "createdAt": "2025-11-12T13:18:32.644Z"
  },
  {
    "id": 181,
    "title": "Penguin Sapiens Non-Fiction",
    "description": "Buy the Penguin Sapiens Non-Fiction from Penguin. Non-Fiction engineered for quality and value. Ideal for books needs.",
    "price": 35.46,
    "category": "Books",
    "rating": 2.4,
    "stock": 383,
    "brand": "Penguin",
    "createdAt": "2025-07-03T03:12:49.677Z"
  },
  {
    "id": 182,
    "title": "Apple QC35 II Wireless Headphones",
    "description": "Buy the Apple QC35 II Wireless Headphones from Apple. Wireless Headphones engineered for quality and value. Ideal for electronics needs.",
    "price": 320.6,
    "category": "Electronics",
    "rating": 4.8,
    "stock": 76,
    "brand": "Apple",
    "createdAt": "2025-08-24T03:00:26.202Z"
  },
  {
    "id": 183,
    "title": "Philips ProBlend Blender",
    "description": "Buy the Philips ProBlend Blender from Philips. Blender engineered for quality and value. Ideal for home needs.",
    "price": 393.21,
    "category": "Home",
    "rating": 3.7,
    "stock": 358,
    "brand": "Philips",
    "createdAt": "2025-12-26T02:47:18.969Z"
  },
  {
    "id": 184,
    "title": "L'Oreal Matte Lipstick",
    "description": "Buy the L'Oreal Matte Lipstick from L'Oreal. Lipstick engineered for quality and value. Ideal for beauty needs.",
    "price": 27.21,
    "category": "Beauty",
    "rating": 3.9,
    "stock": 5,
    "brand": "L'Oreal",
    "createdAt": "2025-03-29T05:03:56.093Z"
  },
  {
    "id": 185,
    "title": "Dyson Cyclone 3000 Vacuum Cleaner",
    "description": "Buy the Dyson Cyclone 3000 Vacuum Cleaner from Dyson. Vacuum Cleaner engineered for quality and value. Ideal for home needs.",
    "price": 474.63,
    "category": "Home",
    "rating": 3.7,
    "stock": 11,
    "brand": "Dyson",
    "createdAt": "2025-05-17T09:00:42.169Z"
  },
  {
    "id": 186,
    "title": "Penguin Educated Non-Fiction",
    "description": "Buy the Penguin Educated Non-Fiction from Penguin. Non-Fiction engineered for quality and value. Ideal for books needs.",
    "price": 28.34,
    "category": "Books",
    "rating": 2.2,
    "stock": 368,
    "brand": "Penguin",
    "createdAt": "2025-03-30T12:15:34.713Z"
  },
  {
    "id": 187,
    "title": "Lenovo ThinkPad X1 Laptop",
    "description": "Buy the Lenovo ThinkPad X1 Laptop from Lenovo. Laptop engineered for quality and value. Ideal for electronics needs.",
    "price": 1411.43,
    "category": "Electronics",
    "rating": 4.7,
    "stock": 64,
    "brand": "Lenovo",
    "createdAt": "2025-07-19T04:44:30.523Z"
  },
  {
    "id": 188,
    "title": "Dell ZenBook 14 Laptop",
    "description": "Buy the Dell ZenBook 14 Laptop from Dell. Laptop engineered for quality and value. Ideal for electronics needs.",
    "price": 1590.85,
    "category": "Electronics",
    "rating": 4.4,
    "stock": 141,
    "brand": "Dell",
    "createdAt": "2025-06-16T03:04:42.438Z"
  },
  {
    "id": 189,
    "title": "Hasbro Mega Blocks Building Blocks",
    "description": "Buy the Hasbro Mega Blocks Building Blocks from Hasbro. Building Blocks engineered for quality and value. Ideal for toys needs.",
    "price": 189.72,
    "category": "Toys",
    "rating": 2.4,
    "stock": 180,
    "brand": "Hasbro",
    "createdAt": "2025-12-14T22:29:58.029Z"
  },
  {
    "id": 190,
    "title": "Hoover PowerSweep Vacuum Cleaner",
    "description": "Buy the Hoover PowerSweep Vacuum Cleaner from Hoover. Vacuum Cleaner engineered for quality and value. Ideal for home needs.",
    "price": 249.05,
    "category": "Home",
    "rating": 4.4,
    "stock": 98,
    "brand": "Hoover",
    "createdAt": "2025-10-24T16:37:23.733Z"
  },
  {
    "id": 191,
    "title": "L'Oreal Satin Lipstick",
    "description": "Buy the L'Oreal Satin Lipstick from L'Oreal. Lipstick engineered for quality and value. Ideal for beauty needs.",
    "price": 28.06,
    "category": "Beauty",
    "rating": 2.8,
    "stock": 157,
    "brand": "L'Oreal",
    "createdAt": "2025-05-23T21:26:11.835Z"
  },
  {
    "id": 192,
    "title": "Cetaphil Daily Cream Moisturizer",
    "description": "Buy the Cetaphil Daily Cream Moisturizer from Cetaphil. Moisturizer engineered for quality and value. Ideal for beauty needs.",
    "price": 7.6,
    "category": "Beauty",
    "rating": 3,
    "stock": 363,
    "brand": "Cetaphil",
    "createdAt": "2026-02-12T01:57:40.362Z"
  },
  {
    "id": 193,
    "title": "Hoover PowerSweep Vacuum Cleaner",
    "description": "Buy the Hoover PowerSweep Vacuum Cleaner from Hoover. Vacuum Cleaner engineered for quality and value. Ideal for home needs.",
    "price": 186.85,
    "category": "Home",
    "rating": 4,
    "stock": 209,
    "brand": "Hoover",
    "createdAt": "2025-10-31T15:47:13.980Z"
  },
  {
    "id": 194,
    "title": "Mega Bloks Mega Blocks Building Blocks",
    "description": "Buy the Mega Bloks Mega Blocks Building Blocks from Mega Bloks. Building Blocks engineered for quality and value. Ideal for toys needs.",
    "price": 92.58,
    "category": "Toys",
    "rating": 4.1,
    "stock": 437,
    "brand": "Mega Bloks",
    "createdAt": "2025-10-30T01:34:11.769Z"
  },
  {
    "id": 195,
    "title": "Dyson Cyclone 3000 Vacuum Cleaner",
    "description": "Buy the Dyson Cyclone 3000 Vacuum Cleaner from Dyson. Vacuum Cleaner engineered for quality and value. Ideal for home needs.",
    "price": 79.25,
    "category": "Home",
    "rating": 1.2,
    "stock": 366,
    "brand": "Dyson",
    "createdAt": "2025-09-14T15:01:16.540Z"
  },
  {
    "id": 196,
    "title": "HarperCollins The Last Kingdom Fiction Book",
    "description": "Buy the HarperCollins The Last Kingdom Fiction Book from HarperCollins. Fiction Book engineered for quality and value. Ideal for books needs.",
    "price": 30.1,
    "category": "Books",
    "rating": 4.8,
    "stock": 243,
    "brand": "HarperCollins",
    "createdAt": "2025-03-29T16:59:41.073Z"
  },
  {
    "id": 197,
    "title": "Lenovo XPS 13 Laptop",
    "description": "Buy the Lenovo XPS 13 Laptop from Lenovo. Laptop engineered for quality and value. Ideal for electronics needs.",
    "price": 1069.01,
    "category": "Electronics",
    "rating": 4.4,
    "stock": 159,
    "brand": "Lenovo",
    "createdAt": "2026-03-09T05:20:49.429Z"
  },
  {
    "id": 198,
    "title": "W.W. Norton Educated Non-Fiction",
    "description": "Buy the W.W. Norton Educated Non-Fiction from W.W. Norton. Non-Fiction engineered for quality and value. Ideal for books needs.",
    "price": 42.71,
    "category": "Books",
    "rating": 2.1,
    "stock": 452,
    "brand": "W.W. Norton",
    "createdAt": "2025-12-16T00:10:07.466Z"
  },
  {
    "id": 199,
    "title": "Nike Classic Tee T-Shirt",
    "description": "Buy the Nike Classic Tee T-Shirt from Nike. T-Shirt engineered for quality and value. Ideal for clothing needs.",
    "price": 9.74,
    "category": "Clothing",
    "rating": 1.3,
    "stock": 417,
    "brand": "Nike",
    "createdAt": "2025-09-14T09:07:32.607Z"
  },
  {
    "id": 200,
    "title": "Converse Air Max Sneakers",
    "description": "Buy the Converse Air Max Sneakers from Converse. Sneakers engineered for quality and value. Ideal for clothing needs.",
    "price": 173.4,
    "category": "Clothing",
    "rating": 1.4,
    "stock": 298,
    "brand": "Converse",
    "createdAt": "2025-08-22T18:21:58.654Z"
  },
  {
    "id": 201,
    "title": "W.W. Norton Atomic Habits Non-Fiction",
    "description": "Buy the W.W. Norton Atomic Habits Non-Fiction from W.W. Norton. Non-Fiction engineered for quality and value. Ideal for books needs.",
    "price": 22.17,
    "category": "Books",
    "rating": 3.4,
    "stock": 350,
    "brand": "W.W. Norton",
    "createdAt": "2025-10-03T16:43:11.274Z"
  },
  {
    "id": 202,
    "title": "New Balance Gel-Nimbus Running Shoes",
    "description": "Buy the New Balance Gel-Nimbus Running Shoes from New Balance. Running Shoes engineered for quality and value. Ideal for sports needs.",
    "price": 119.13,
    "category": "Sports",
    "rating": 3.8,
    "stock": 472,
    "brand": "New Balance",
    "createdAt": "2026-01-19T02:44:49.214Z"
  },
  {
    "id": 203,
    "title": "Philips ProBlend Blender",
    "description": "Buy the Philips ProBlend Blender from Philips. Blender engineered for quality and value. Ideal for home needs.",
    "price": 224.18,
    "category": "Home",
    "rating": 4.6,
    "stock": 431,
    "brand": "Philips",
    "createdAt": "2025-03-17T14:52:14.737Z"
  },
  {
    "id": 204,
    "title": "Adidas Ultraboost Sneakers",
    "description": "Buy the Adidas Ultraboost Sneakers from Adidas. Sneakers engineered for quality and value. Ideal for clothing needs.",
    "price": 158.42,
    "category": "Clothing",
    "rating": 1.2,
    "stock": 90,
    "brand": "Adidas",
    "createdAt": "2026-03-04T23:53:22.930Z"
  },
  {
    "id": 205,
    "title": "Ninja SmoothieX Blender",
    "description": "Buy the Ninja SmoothieX Blender from Ninja. Blender engineered for quality and value. Ideal for home needs.",
    "price": 140.38,
    "category": "Home",
    "rating": 3.1,
    "stock": 449,
    "brand": "Ninja",
    "createdAt": "2026-02-26T08:50:53.224Z"
  },
  {
    "id": 206,
    "title": "Olay HydraBoost Moisturizer",
    "description": "Buy the Olay HydraBoost Moisturizer from Olay. Moisturizer engineered for quality and value. Ideal for beauty needs.",
    "price": 31.38,
    "category": "Beauty",
    "rating": 3.4,
    "stock": 269,
    "brand": "Olay",
    "createdAt": "2025-10-05T06:57:46.530Z"
  },
  {
    "id": 207,
    "title": "Manduka EcoMat Yoga Mat",
    "description": "Buy the Manduka EcoMat Yoga Mat from Manduka. Yoga Mat engineered for quality and value. Ideal for sports needs.",
    "price": 39.69,
    "category": "Sports",
    "rating": 1.7,
    "stock": 115,
    "brand": "Manduka",
    "createdAt": "2025-03-31T17:51:37.592Z"
  },
  {
    "id": 208,
    "title": "Philips ProBlend Blender",
    "description": "Buy the Philips ProBlend Blender from Philips. Blender engineered for quality and value. Ideal for home needs.",
    "price": 324.7,
    "category": "Home",
    "rating": 4.1,
    "stock": 101,
    "brand": "Philips",
    "createdAt": "2025-12-09T13:08:29.442Z"
  },
  {
    "id": 209,
    "title": "Levi's Bootcut Jeans",
    "description": "Buy the Levi's Bootcut Jeans from Levi's. Jeans engineered for quality and value. Ideal for clothing needs.",
    "price": 188.31,
    "category": "Clothing",
    "rating": 4.7,
    "stock": 198,
    "brand": "Levi's",
    "createdAt": "2026-02-18T15:52:55.595Z"
  },
  {
    "id": 210,
    "title": "KitchenAid ProBlend Blender",
    "description": "Buy the KitchenAid ProBlend Blender from KitchenAid. Blender engineered for quality and value. Ideal for home needs.",
    "price": 246.68,
    "category": "Home",
    "rating": 1.6,
    "stock": 286,
    "brand": "KitchenAid",
    "createdAt": "2025-05-17T20:05:58.202Z"
  },
  {
    "id": 211,
    "title": "Converse Chuck Taylor Sneakers",
    "description": "Buy the Converse Chuck Taylor Sneakers from Converse. Sneakers engineered for quality and value. Ideal for clothing needs.",
    "price": 167.14,
    "category": "Clothing",
    "rating": 1.9,
    "stock": 17,
    "brand": "Converse",
    "createdAt": "2026-03-07T04:39:24.332Z"
  },
  {
    "id": 212,
    "title": "Olay Daily Cream Moisturizer",
    "description": "Buy the Olay Daily Cream Moisturizer from Olay. Moisturizer engineered for quality and value. Ideal for beauty needs.",
    "price": 72.84,
    "category": "Beauty",
    "rating": 4.6,
    "stock": 137,
    "brand": "Olay",
    "createdAt": "2026-02-04T08:23:42.489Z"
  },
  {
    "id": 213,
    "title": "ASICS Gel-Nimbus Running Shoes",
    "description": "Buy the ASICS Gel-Nimbus Running Shoes from ASICS. Running Shoes engineered for quality and value. Ideal for sports needs.",
    "price": 91.34,
    "category": "Sports",
    "rating": 4.2,
    "stock": 104,
    "brand": "ASICS",
    "createdAt": "2025-06-26T12:53:51.282Z"
  },
  {
    "id": 214,
    "title": "Hoover PowerSweep Vacuum Cleaner",
    "description": "Buy the Hoover PowerSweep Vacuum Cleaner from Hoover. Vacuum Cleaner engineered for quality and value. Ideal for home needs.",
    "price": 429.45,
    "category": "Home",
    "rating": 2.4,
    "stock": 103,
    "brand": "Hoover",
    "createdAt": "2025-05-19T12:40:13.030Z"
  },
  {
    "id": 215,
    "title": "ASICS Gel-Nimbus Running Shoes",
    "description": "Buy the ASICS Gel-Nimbus Running Shoes from ASICS. Running Shoes engineered for quality and value. Ideal for sports needs.",
    "price": 144.4,
    "category": "Sports",
    "rating": 3,
    "stock": 137,
    "brand": "ASICS",
    "createdAt": "2025-05-26T11:29:12.114Z"
  },
  {
    "id": 216,
    "title": "Asus MacBook Air Laptop",
    "description": "Buy the Asus MacBook Air Laptop from Asus. Laptop engineered for quality and value. Ideal for electronics needs.",
    "price": 2478.93,
    "category": "Electronics",
    "rating": 2,
    "stock": 253,
    "brand": "Asus",
    "createdAt": "2025-12-12T19:02:42.130Z"
  },
  {
    "id": 217,
    "title": "Mega Bloks Mega Blocks Building Blocks",
    "description": "Buy the Mega Bloks Mega Blocks Building Blocks from Mega Bloks. Building Blocks engineered for quality and value. Ideal for toys needs.",
    "price": 177.57,
    "category": "Toys",
    "rating": 3.7,
    "stock": 9,
    "brand": "Mega Bloks",
    "createdAt": "2025-11-02T09:41:08.668Z"
  },
  {
    "id": 218,
    "title": "Lululemon ProGrip Yoga Mat",
    "description": "Buy the Lululemon ProGrip Yoga Mat from Lululemon. Yoga Mat engineered for quality and value. Ideal for sports needs.",
    "price": 26.18,
    "category": "Sports",
    "rating": 4.8,
    "stock": 497,
    "brand": "Lululemon",
    "createdAt": "2026-02-09T20:56:34.439Z"
  },
  {
    "id": 219,
    "title": "Hoover Cyclone 3000 Vacuum Cleaner",
    "description": "Buy the Hoover Cyclone 3000 Vacuum Cleaner from Hoover. Vacuum Cleaner engineered for quality and value. Ideal for home needs.",
    "price": 576.75,
    "category": "Home",
    "rating": 1.4,
    "stock": 435,
    "brand": "Hoover",
    "createdAt": "2026-03-09T20:10:18.213Z"
  },
  {
    "id": 220,
    "title": "Google Watch Series 6 Smartwatch",
    "description": "Buy the Google Watch Series 6 Smartwatch from Google. Smartwatch engineered for quality and value. Ideal for electronics needs.",
    "price": 280.6,
    "category": "Electronics",
    "rating": 2.2,
    "stock": 284,
    "brand": "Google",
    "createdAt": "2025-04-04T19:39:38.818Z"
  }
]